CON_ALU/CON_ALU.v
module CON_ALU(
  input [7:0] A,
  input [7:0] B,
  input [3:0] SELC,
  output [7:0] ALU_OUT,
  output reg CF,
  output reg ZF,
  output reg SF
);

wire [8:0] t;
assign t = {1'b0,A} + {1'b0,B};   
reg [7:0] RES;
reg temp_CF; // Temporary variable for CF

initial begin
  CF = 1'b0;
  ZF = 1'b0;
  SF = 1'b0;
end

always @* begin 
  temp_CF = t[8]; // Compute CF
  case(SELC)
    4'b0000: RES = A + B; // Addition
    4'b0001: RES = A - B; // Subtraction 
    4'b0010: RES = A * B; // Multiplication
    4'b0011: RES = A / B; // Division
    4'b0100: RES = A << 1; // Logical shift left
    4'b0101: RES = A >> 1; // Logical shift right
    4'b0110: RES = {A[6:0],A[7]}; // Rotate left
    4'b0111: RES = {A[0],A[7:1]}; // Rotate right
    4'b1000: RES = A & B; // Logical and 
    4'b1001: RES = A | B; // Logical or
    4'b1010: RES = A ^ B; // Logical xor 
    4'b1011: RES = ~(A | B); // Logical nor
    4'b1100: RES = ~(A & B); // Logical nand 
    4'b1101: RES = ~(A ^ B); // Logical xnor
    4'b1110: begin // Greater comparison
      if (A > B) begin
        RES = 8'd1;
        temp_CF = 1'b1;
        ZF = 1'b0;
        SF = 1'b0;
      end
      else begin
        RES = 8'd0;
        temp_CF = 1'b0;
        ZF = 1'b0;
        SF = 1'b0;
      end
    end
    4'b1111: begin // Equal comparison 
      if (A == B) begin
        RES = 8'd1;
        temp_CF = 1'b0;
        ZF = 1'b1;
        SF = 1'b0;
      end
      else begin
        RES = 8'd0;
        temp_CF = 1'b0;
        ZF = 1'b0;
        SF = 1'b0;
      end
    end
    default: begin
      RES = A + B;
      temp_CF = 1'b0;
      ZF = 1'b0;
      SF = 1'b0;
    end
  endcase
  CF = temp_CF; // Assign CF
end

assign ALU_OUT = RES;

endmodule

CON_ALU/TB_CON_ALU.v
module TB_CON_ALU;

reg [7:0] A, B;
reg [3:0] SELC;
wire [7:0] ALU_OUT;
wire CF;
wire ZF, SF;

// Instantiate the Unit Under Test (UUT)
CON_ALU uut (
    .A(A),
    .B(B),
    .SELC(SELC),
    .ALU_OUT(ALU_OUT),
    .CF(CF),
    .ZF(ZF),
    .SF(SF)
);

// Initialize Inputs
initial begin
    A = 8'b00000000;
    B = 8'b00000000;
    SELC = 4'b0000;

    // Add more test cases here
    #10 A = 8'b00001100; B = 8'b00100010; SELC = 4'b0000; // A + B
    #10 A = 8'b01001100; B = 8'b00011111; SELC = 4'b0001; // A - B
    #10 A = 8'b01001100; B = 8'b00011111; SELC = 4'b0010; // A * B
    #10 A = 8'b10010000; B = 8'b00001000; SELC = 4'b0011; // A / B
    #10 A = 8'b00000101; B = 8'b00001010; SELC = 4'b0100; // A << 1
    #10 A = 8'b11110000; B = 8'b00000001; SELC = 4'b0101; // A >> 1
    #10 A = 8'b00001010; B = 8'b00000010; SELC = 4'b0110; // Rotate left
    #10 A = 8'b11110000; B = 8'b00000001; SELC = 4'b0111; // Rotate right
    #10 A = 8'b11110000; B = 8'b00001111; SELC = 4'b1000; // Logical and
    #10 A = 8'b11110000; B = 8'b00001111; SELC = 4'b1001; // Logical or
    #10 A = 8'b11110000; B = 8'b00001111; SELC = 4'b1010; // Logical xor
    #10 A = 8'b11110000; B = 8'b00001111; SELC = 4'b1011; // Logical nor
    #10 A = 8'b11110000; B = 8'b00001111; SELC = 4'b1100; // Logical nand
    #10 A = 8'b11110000; B = 8'b00001111; SELC = 4'b1101; // Logical xnor
    #10 A = 8'b11110000; B = 8'b00001111; SELC = 4'b1110; // Greater comparison
    #10 A = 8'b11110000; B = 8'b11110000; SELC = 4'b1110; // Greater comparison (equal)
    #10 A = 8'b11110000; B = 8'b11110000; SELC = 4'b1111; // Equal comparison
    #10 $finish;
end

initial begin
    $dumpfile("waveforms.vcd");
    $dumpvars(0, TB_CON_ALU);
end

// Display results
always @* begin
    case(SELC)
      4'b0000: $display("Operation: Addition, A = %h, B = %h, ALU_OUT = %h, CF = %b, ZF = %b, SF = %b", A, B, ALU_OUT, CF, ZF, SF);
      4'b0001: $display("Operation: Subtraction, A = %h, B = %h, ALU_OUT = %h, CF = %b, ZF = %b, SF = %b", A, B, ALU_OUT, CF, ZF, SF);
      4'b0010: $display("Operation: Multiplication, A = %h, B = %h, ALU_OUT = %h, CF = %b, ZF = %b, SF = %b", A, B, ALU_OUT, CF, ZF, SF);
      4'b0011: $display("Operation: Division, A = %h, B = %h, ALU_OUT = %h, CF = %b, ZF = %b, SF = %b", A, B, ALU_OUT, CF, ZF, SF);
      4'b0100: $display("Operation: Logical shift left, A = %h, B = %h, ALU_OUT = %h, CF = %b, ZF = %b, SF = %b", A, B, ALU_OUT, CF, ZF, SF);
      4'b0101: $display("Operation: Logical shift right, A = %h, B = %h, ALU_OUT = %h, CF = %b, ZF = %b, SF = %b", A, B, ALU_OUT, CF, ZF, SF);
      4'b0110: $display("Operation: Rotate left, A = %h, B = %h, ALU_OUT = %h, CF = %b, ZF = %b, SF = %b", A, B, ALU_OUT, CF, ZF, SF);
      4'b0111: $display("Operation: Rotate right, A = %h, B = %h, ALU_OUT = %h, CF = %b, ZF = %b, SF = %b", A, B, ALU_OUT, CF, ZF, SF);
      4'b1000: $display("Operation: Logical and, A = %h, B = %h, ALU_OUT = %h, CF = %b, ZF = %b, SF = %b", A, B, ALU_OUT, CF, ZF, SF);
      4'b1001: $display("Operation: Logical or, A = %h, B = %h, ALU_OUT = %h, CF = %b, ZF = %b, SF = %b", A, B, ALU_OUT, CF, ZF, SF);
      4'b1010: $display("Operation: Logical xor, A = %h, B = %h, ALU_OUT = %h, CF = %b, ZF = %b, SF = %b", A, B, ALU_OUT, CF, ZF, SF);
      4'b1011: $display("Operation: Logical nor, A = %h, B = %h, ALU_OUT = %h, CF = %b, ZF = %b, SF = %b", A, B, ALU_OUT, CF, ZF, SF);
      4'b1100: $display("Operation: Logical nand, A = %h, B = %h, ALU_OUT = %h, CF = %b, ZF = %b, SF = %b", A, B, ALU_OUT, CF, ZF, SF);
      4'b1101: $display("Operation: Logical xnor, A = %h, B = %h, ALU_OUT = %h, CF = %b, ZF = %b, SF = %b", A, B, ALU_OUT, CF, ZF, SF);
      4'b1110: $display("Operation: Greater comparison, A = %h, B = %h, ALU_OUT = %h, CF = %b, ZF = %b, SF = %b", A, B, ALU_OUT, CF, ZF, SF);
      4'b1111: $display("Operation: Equal comparison, A = %h, B = %h, ALU_OUT = %h, CF = %b, ZF = %b, SF = %b", A, B, ALU_OUT, CF, ZF, SF);
      default: $display("Unknown operation, A = %h, B = %h, ALU_OUT = %h, CF = %b, ZF = %b, SF = %b", A, B, ALU_OUT, CF, ZF, SF);
    endcase
end

endmodule

CON_ALU/waveforms.vcd
$date
	Sun Apr 14 03:45:58 2024
$end
$version
	ModelSim Version 10.6d
$end
$timescale
	1ns
$end

$scope module TB_CON_ALU $end
$var reg 8 ! A [7:0] $end
$var reg 8 " B [7:0] $end
$var reg 4 # SELC [3:0] $end
$var wire 1 $ ALU_OUT [7] $end
$var wire 1 % ALU_OUT [6] $end
$var wire 1 & ALU_OUT [5] $end
$var wire 1 ' ALU_OUT [4] $end
$var wire 1 ( ALU_OUT [3] $end
$var wire 1 ) ALU_OUT [2] $end
$var wire 1 * ALU_OUT [1] $end
$var wire 1 + ALU_OUT [0] $end
$var wire 1 , CF $end
$var wire 1 - ZF $end
$var wire 1 . SF $end

$scope module uut $end
$var wire 1 / A [7] $end
$var wire 1 0 A [6] $end
$var wire 1 1 A [5] $end
$var wire 1 2 A [4] $end
$var wire 1 3 A [3] $end
$var wire 1 4 A [2] $end
$var wire 1 5 A [1] $end
$var wire 1 6 A [0] $end
$var wire 1 7 B [7] $end
$var wire 1 8 B [6] $end
$var wire 1 9 B [5] $end
$var wire 1 : B [4] $end
$var wire 1 ; B [3] $end
$var wire 1 < B [2] $end
$var wire 1 = B [1] $end
$var wire 1 > B [0] $end
$var wire 1 ? SELC [3] $end
$var wire 1 @ SELC [2] $end
$var wire 1 A SELC [1] $end
$var wire 1 B SELC [0] $end
$var wire 1 $ ALU_OUT [7] $end
$var wire 1 % ALU_OUT [6] $end
$var wire 1 & ALU_OUT [5] $end
$var wire 1 ' ALU_OUT [4] $end
$var wire 1 ( ALU_OUT [3] $end
$var wire 1 ) ALU_OUT [2] $end
$var wire 1 * ALU_OUT [1] $end
$var wire 1 + ALU_OUT [0] $end
$var reg 1 C CF $end
$var reg 1 D ZF $end
$var reg 1 E SF $end
$var wire 1 F t [8] $end
$var wire 1 G t [7] $end
$var wire 1 H t [6] $end
$var wire 1 I t [5] $end
$var wire 1 J t [4] $end
$var wire 1 K t [3] $end
$var wire 1 L t [2] $end
$var wire 1 M t [1] $end
$var wire 1 N t [0] $end
$var reg 8 O RES [7:0] $end
$var reg 1 P temp_CF $end
$upscope $end
$upscope $end
$enddefinitions $end
#0
$dumpvars
b0 !
b0 "
b0 #
0C
0D
0E
b0 O
0P
0+
0*
0)
0(
0'
0&
0%
0$
0,
0-
0.
0N
0M
0L
0K
0J
0I
0H
0G
0F
0B
0A
0@
0?
0>
0=
0<
0;
0:
09
08
07
06
05
04
03
02
01
00
0/
$end
#10
b1100 !
b100010 "
1=
19
14
13
1M
1L
1K
1I
b101110 O
1*
1)
1(
1&
#20
b1001100 !
b11111 "
b1 #
1B
1>
1<
1;
1:
09
10
1N
0L
1H
b101101 O
1+
0*
#30
b10 #
0B
1A
b110100 O
0+
0(
1'
#40
b10010000 !
b1000 "
b11 #
1B
0>
0=
0<
0:
04
03
12
00
1/
0N
0M
1J
0I
0H
1G
b10010 O
1*
0)
0&
#50
b101 !
b1010 "
b100 #
0B
0A
1@
1=
16
14
02
0/
1N
1M
1L
0J
0G
b1010 O
1(
0'
#60
b11110000 !
b1 "
b101 #
1B
1>
0=
0;
06
04
12
11
10
1/
0M
0L
0K
1J
1I
1H
1G
b1111000 O
0*
1'
1&
1%
#70
b1010 !
b10 "
b110 #
0B
1A
0>
1=
15
13
02
01
00
0/
0N
1L
1K
0J
0I
0H
0G
b10100 O
1)
0(
0&
0%
#80
b11110000 !
b1 "
b111 #
1B
1>
0=
05
03
12
11
10
1/
1N
0L
0K
1J
1I
1H
1G
b1111000 O
0)
1(
1&
1%
#90
b1111 "
b1000 #
0B
0A
0@
1?
1=
1<
1;
1M
1L
1K
b0 O
0(
0'
0&
0%
#100
b1001 #
1B
b11111111 O
1+
1*
1)
1(
1'
1&
1%
1$
#110
b1010 #
0B
1A
#120
b1011 #
1B
b0 O
0+
0*
0)
0(
0'
0&
0%
0$
#130
b1100 #
0B
0A
1@
b11111111 O
1+
1*
1)
1(
1'
1&
1%
1$
#140
b1101 #
1B
b0 O
0+
0*
0)
0(
0'
0&
0%
0$
#150
b1110 #
0B
1A
b1 O
1P
1C
1+
1,
#160
b11110000 "
0>
0=
0<
0;
1:
19
18
17
0N
0M
0L
0K
0J
1F
b0 O
0P
0C
0+
0,
#170
b1111 #
1B
1P
b1 O
0P
1D
1+
1-
